gptsql/__init__.py
gptsql/__main__.py
gptsql/func_tools.py
gptsql/utils.py
gptsql-0.1.7.dist-info/WHEEL
gptsql-0.1.7.dist-info/entry_points.txt
gptsql-0.1.7.dist-info/METADATA
gptsql-0.1.7.dist-info/RECORD
