Metadata-Version: 2.1
Name: gptsql
Version: 0.1.7
Summary: LLM-powered chat interface to your Postgres database
Author: Scott Persinger
Author-email: scottpersinger@gmail.com
Requires-Python: >=3.9,<4.0
Classifier: Programming Language :: Python :: 3
Classifier: Programming Language :: Python :: 3.9
Classifier: Programming Language :: Python :: 3.10
Classifier: Programming Language :: Python :: 3.11
Requires-Dist: halo (>=0.0.31,<0.0.32)
Requires-Dist: openai (>=1.3.6,<2.0.0)
Requires-Dist: pandas (>=2.1.3,<3.0.0)
Requires-Dist: prompt-toolkit (>=3.0.41,<4.0.0)
Requires-Dist: psycopg2 (>=2.9.9,<3.0.0)
Requires-Dist: sqlalchemy (>=2.0.23,<3.0.0)
Requires-Dist: tabulate (>=0.9.0,<0.10.0)
Requires-Dist: termcolor (>=2.3.0,<3.0.0)
Requires-Dist: toml (>=0.10.2,<0.11.0)
